MANIFEST.in
README.txt
setup.py
collective/__init__.py
collective.setuphandlertools.egg-info/PKG-INFO
collective.setuphandlertools.egg-info/SOURCES.txt
collective.setuphandlertools.egg-info/dependency_links.txt
collective.setuphandlertools.egg-info/namespace_packages.txt
collective.setuphandlertools.egg-info/not-zip-safe
collective.setuphandlertools.egg-info/requires.txt
collective.setuphandlertools.egg-info/top_level.txt
collective/setuphandlertools/__init__.py
collective/setuphandlertools/setuphandlertools.py
docs/HISTORY.txt
docs/INSTALL.txt
docs/LICENSE.GPL
docs/LICENSE.txt