Metadata-Version: 1.0
Name: collective.setuphandlertools
Version: 1.0b4
Summary: Tools for setting up a Plone site.
Home-page: http://github.com/collective/collective.setuphandlertools
Author: Johannes Raggam
Author-email: raggam-nl@adm.at
License: GPL
Keywords: plone zope setup
Platform: UNKNOWN
Classifier: Framework :: Plone
Classifier: Programming Language :: Python
